bibliophile/__init__.py
bibliophile/bibliocommons/__init__.py
bibliophile/bibliocommons/errors.py
bibliophile/bibliocommons/parse.py
bibliophile/bibliocommons/query.py
bibliophile/bibliocommons/types.py
bibliophile/errors.py
bibliophile/goodreads/__init__.py
bibliophile/goodreads/images.py
bibliophile/goodreads/shelf.py
bibliophile/goodreads/types.py
bibliophile/py.typed
bibliophile/syndetics.py
bibliophile/tests/__init__.py
bibliophile/tests/bibliocommons/__init__.py
bibliophile/tests/bibliocommons/test_parse.py
bibliophile/tests/bibliocommons/test_query.py
bibliophile/tests/goodreads/__init__.py
bibliophile/tests/goodreads/test_images.py
bibliophile/tests/goodreads/test_shelf.py
bibliophile/tests/test_syndetics.py
bibliophile-1.0.0.dist-info/LICENSE.md
bibliophile-1.0.0.dist-info/WHEEL
bibliophile-1.0.0.dist-info/METADATA
bibliophile-1.0.0.dist-info/RECORD
