Metadata-Version: 2.1
Name: bibliophile
Version: 1.0.0
Summary: Find books at your local library
Home-page: https://biblo.dcain.me
License: GPL-3.0
Author: David Cain
Author-email: davidjosephcain@gmail.com
Requires-Python: >=3.6,<4.0
Classifier: License :: OSI Approved :: GNU General Public License v3 (GPLv3)
Classifier: Programming Language :: Python :: 3
Classifier: Programming Language :: Python :: 3.6
Classifier: Programming Language :: Python :: 3.7
Classifier: Programming Language :: Python :: 3.8
Classifier: Programming Language :: Python :: 3.9
Requires-Dist: beautifulsoup4
Requires-Dist: grequests
Requires-Dist: lxml
Requires-Dist: requests
Project-URL: Repository, https://github.com/DavidCain/bibliophile-backend/
